draco/__init__.py
draco/asp/constraints.lp
draco/asp/define.lp
draco/asp/examples/binned_histogram.lp
draco/asp/examples/histogram.lp
draco/asp/examples/scatter.lp
draco/asp/generate.lp
draco/asp/hard.lp
draco/asp/helpers.lp
draco/asp/optimize.lp
draco/asp/soft.lp
draco/asp/weights.lp
draco/asp_utils.py
draco/data_utils.py
draco/debug.py
draco/draco.py
draco/fact_utils.py
draco/learn.py
draco/programs.py
draco/renderer/__init__.py
draco/renderer/altair/__init__.py
draco/renderer/altair/altair_renderer.py
draco/renderer/altair/types.py
draco/renderer/base_renderer.py
draco/run.py
draco/schema.py
draco/server/__init__.py
draco/server/__main__.py
draco/server/draco_api.py
draco/server/main.py
draco/server/models/__init__.py
draco/server/models/clingo.py
draco/server/models/draco.py
draco/server/models/renderer.py
draco/server/models/shared.py
draco/server/models/utility.py
draco/server/routers/__init__.py
draco/server/routers/base.py
draco/server/routers/clingo.py
draco/server/routers/draco.py
draco/server/routers/renderer.py
draco/server/routers/utility.py
draco/server/services/__init__.py
draco/server/services/clingo.py
draco/server/services/draco.py
draco/server/services/renderer.py
draco/server/services/utility.py
draco/server/utils.py
draco/types.py
draco/utils.py
draco/weights.py
draco-2.0.1.dist-info/LICENSE
draco-2.0.1.dist-info/METADATA
draco-2.0.1.dist-info/WHEEL
draco-2.0.1.dist-info/RECORD
