Metadata-Version: 2.1
Name: draco
Version: 2.0.1
Summary: Visualization recommendation using constraints
Home-page: https://github.com/cmudig/draco2
License: MIT
Keywords: constraints,visualization,design,charts
Author: Dominik Moritz
Author-email: domoritz@cmu.edu
Requires-Python: >=3.10.0,<3.12
Classifier: Development Status :: 4 - Beta
Classifier: Environment :: Console
Classifier: Environment :: MacOS X
Classifier: Framework :: FastAPI
Classifier: Framework :: Jupyter
Classifier: Framework :: Pydantic
Classifier: Framework :: Pytest
Classifier: License :: OSI Approved :: MIT License
Classifier: Natural Language :: English
Classifier: Operating System :: MacOS :: MacOS X
Classifier: Operating System :: POSIX :: Linux
Classifier: Programming Language :: Python :: 3
Classifier: Programming Language :: Python :: 3.10
Classifier: Programming Language :: Python :: 3.11
Requires-Dist: altair (>=5.2.0,<6.0.0)
Requires-Dist: clingo (>=5.5.2,<6.0.0)
Requires-Dist: fastapi (>=0.108,<0.200)
Requires-Dist: pandas (>=2.1.4,<3.0.0)
Requires-Dist: pydantic (>=2.5.3,<3.0.0)
Requires-Dist: scikit-learn (>=1.3.2,<2.0.0)
Requires-Dist: tabulate (>=0.9.0,<0.10.0)
Requires-Dist: uvicorn (>=0.25.0,<0.30.0)
Project-URL: Documentation, https://dig.cmu.edu/draco2/
Project-URL: Repository, https://github.com/cmudig/draco2
